[
  {
    "id": 7,
    "projectTitle": "PlanX",
    "category": "Education Website",
    "description": "",
    "myRole": "",
    "videoSrc": "",
    "imgCover": "",
    "img1": "",
    "img2": "",
    "img3": ""
  },
  {
    "id": 8,
    "projectTitle": "",
    "category": "",
    "description": "",
    "myRole": "",
    "videoSrc": "",
    "imgCover": "",
    "img1": "",
    "img2": "",
    "img3": ""
  },
  {
    "id": 9,
    "projectTitle": "",
    "category": "",
    "description": "",
    "myRole": "",
    "videoSrc": "",
    "imgCover": "",
    "img1": "",
    "img2": "",
    "img3": ""
  },
  {
    "id": 10,
    "projectTitle": "",
    "category": "",
    "description": "",
    "myRole": "",
    "videoSrc": "",
    "imgCover": "",
    "img1": "",
    "img2": "",
    "img3": ""
  },
  {
    "id": 11,
    "projectTitle": "",
    "category": "",
    "description": "",
    "myRole": "",
    "videoSrc": "",
    "imgCover": "",
    "img1": "",
    "img2": "",
    "img3": ""
  },
  {
    "id": 12,
    "projectTitle": "",
    "category": "",
    "description": "",
    "myRole": "",
    "videoSrc": "",
    "imgCover": "",
    "img1": "",
    "img2": "",
    "img3": ""
  }
]
